tdaspop/__init__.py
tdaspop/pop_dists.py
tdaspop/population_params_absracts.py
tdaspop/rateDistributions.py
tdaspop/sampling.py
tdaspop/version.py
tdaspop-0.2.0.dist-info/LICENSE
tdaspop-0.2.0.dist-info/METADATA
tdaspop-0.2.0.dist-info/WHEEL
tdaspop-0.2.0.dist-info/top_level.txt
tdaspop-0.2.0.dist-info/RECORD
