Metadata-Version: 2.1
Name: tdaspop
Version: 0.2.0
Summary: classes to describe rates and population parameters of variables and sample them
Home-page: UNKNOWN
Author: UNKNOWN
Author-email: UNKNOWN
License: UNKNOWN
Platform: UNKNOWN
